{
  "name": "ubuntu:22.04-LLVM:15",
  "build": {
    "dockerfile": "Dockerfile"
  },
  "features": {
    "ghcr.io/devcontainers-extra/features/fish-apt-get:1": {},
    "ghcr.io/devcontainers/features/git:1": {},
    "ghcr.io/devcontainers/features/python": {
      "version": "3.11"
    },
    "ghcr.io/devcontainers/features/sshd:1": {
      "version": "latest"
    },
    // Switch to the "official" version as soon as
    // https://github.com/devcontainers-community/features-cmake/pull/2
    // merged
    "ghcr.io/alexdenisov/features/feature-cmake": {
      "version": "3.31.1"
    }
  },
  "postCreateCommand": "infrastructure/devcontainer_post_create.sh ubuntu 15",
  "customizations": {
    "vscode": {
      "extensions": [
        "ms-vscode.cmake-tools",
        "ms-vscode.cpptools",
        "ms-vscode.cpptools-extension-pack",
        "imgildev.vscode-mustache-snippets",
        "github.vscode-github-actions",
        "revng.llvm-ir",
        "rreverser.llvm"
      ]
    }
  }
}
